ipfs_node/__init__.py
ipfs_node/ipfs_files.py
ipfs_node/ipfs_node.py
ipfs_node/ipfs_peers.py
ipfs_node/ipfs_pubsub.py
ipfs_node/ipfs_tunnels.py
ipfs_node/libkubo/libkubo_linux_x86_64.h
ipfs_node/libkubo/libkubo_linux_x86_64.so
ipfs_node/utils/__init__.py
ipfs_node/utils/cid_utils.py
ipfs_node/utils/peer_utils.py
libkubo/__init__.py
libkubo/libkubo_loader.py
kubo_python-0.1.5.dist-info/LICENSE
kubo_python-0.1.5.dist-info/METADATA
kubo_python-0.1.5.dist-info/WHEEL
kubo_python-0.1.5.dist-info/top_level.txt
kubo_python-0.1.5.dist-info/RECORD
