Metadata-Version: 2.1
Name: kubo-python
Version: 0.1.5
Summary: Run an IPFS node inside of python using kubo as a library.
Home-page: https://github.com/emendir/py_ipfs_node
Author: Emendir
Author-email: 
Classifier: Programming Language :: Python :: 3
Classifier: License :: OSI Approved :: MIT License
Classifier: Operating System :: OS Independent
Requires-Python: >=3.7
License-File: LICENSE
Requires-Dist: cffi >=1.15.0
